{
  "code": "0",
  "data": {
    "totalCount": 13,
    "template": "pcfood",
    "searchResult": [
      {
        "id": 88634213,
        "template": "pcfood",
        "imageUrl": "http://p0.meituan.net/w.h/ugcpic/9604b9c54ed7cae610b39a34b36dce41801628.png",
        "title": "京北爱宠宠物医院（东光店）",
        "address": "东光茧城大街与东升路交叉口北",
        "lowestprice": 0.0,
        "avgprice": 0.0,
        "latitude": 37.884024,
        "longitude": 116.557298,
        "showType": "easylife",
        "avgscore": 0.0,
        "comments": 0,
        "historyCouponCount": 0,
        "backCateName": "宠物医院",
        "areaname": "东光",
        "tag": [],
        "cate": [
          3,
          20691
        ],
        "recentScreen": null,
        "abstracts": [],
        "dangleAbstracts": null,
        "titleTags": [],
        "iUrl": null,
        "deals": null,
        "posdescr": null,
        "ct_poi": null,
        "trace": null,
        "landmarkDistance": null,
        "hasAds": false,
        "adsClickUrl": "",
        "adsShowUrl": "",
        "distance": "",
        "cityId": 127,
        "city": "沧州",
        "full": false
      },
      {
        "id": 177490778,
        "template": "pcfood",
        "imageUrl": "http://p0.meituan.net/w.h/dpdeal/af214371dc6b102325ac8cfad65987d146949.jpg",
        "title": "旺旺爱宠",
        "address": "东光步行街134号",
        "lowestprice": 0.0,
        "avgprice": 0.0,
        "latitude": 37.880184,
        "longitude": 116.670382,
        "showType": "easylife",
        "avgscore": 0.0,
        "comments": 0,
        "historyCouponCount": 0,
        "backCateName": "宠物店",
        "areaname": "东光",
        "tag": [],
        "cate": [
          3,
          20691,
          20630
        ],
        "recentScreen": null,
        "abstracts": [],
        "dangleAbstracts": null,
        "titleTags": [],
        "iUrl": null,
        "deals": null,
        "posdescr": null,
        "ct_poi": null,
        "trace": null,
        "landmarkDistance": null,
        "hasAds": false,
        "adsClickUrl": "",
        "adsShowUrl": "",
        "distance": "",
        "cityId": 0,
        "city": "",
        "full": false
      },
      {
        "id": 50474252,
        "template": "pcfood",
        "imageUrl": "http://p0.meituan.net/w.h/ugcpic/9604b9c54ed7cae610b39a34b36dce41801628.png",
        "title": "深蓝水族馆",
        "address": "育才大街育才大街第一中学东北80米",
        "lowestprice": 0.0,
        "avgprice": 0.0,
        "latitude": 37.881667,
        "longitude": 116.54082,
        "showType": "easylife",
        "avgscore": 3.5,
        "comments": 0,
        "historyCouponCount": 0,
        "backCateName": "其他宠物",
        "areaname": "育才大街",
        "tag": [],
        "cate": [
          3,
          20691
        ],
        "recentScreen": null,
        "abstracts": [],
        "dangleAbstracts": null,
        "titleTags": [],
        "iUrl": null,
        "deals": null,
        "posdescr": null,
        "ct_poi": null,
        "trace": null,
        "landmarkDistance": null,
        "hasAds": false,
        "adsClickUrl": "",
        "adsShowUrl": "",
        "distance": "",
        "cityId": 127,
        "city": "沧州",
        "full": false
      },
      {
        "id": 177493908,
        "template": "pcfood",
        "imageUrl": "http://p1.meituan.net/w.h/dpdeal/6d3e0a5993c7c4b6ca9fd596385fc980113745.jpg",
        "title": "爱宠屋",
        "address": "东光东升路西100米（东开骏景西区底商）",
        "lowestprice": 0.0,
        "avgprice": 0.0,
        "latitude": 37.891905,
        "longitude": 116.558494,
        "showType": "easylife",
        "avgscore": 0.0,
        "comments": 0,
        "historyCouponCount": 0,
        "backCateName": "宠物店",
        "areaname": "东光",
        "tag": [],
        "cate": [
          3,
          20691,
          20630
        ],
        "recentScreen": null,
        "abstracts": [],
        "dangleAbstracts": null,
        "titleTags": [],
        "iUrl": null,
        "deals": null,
        "posdescr": null,
        "ct_poi": null,
        "trace": null,
        "landmarkDistance": null,
        "hasAds": false,
        "adsClickUrl": "",
        "adsShowUrl": "",
        "distance": "",
        "cityId": 0,
        "city": "",
        "full": false
      },
      {
        "id": 50908694,
        "template": "pcfood",
        "imageUrl": "http://p0.meituan.net/w.h/ugcpic/9604b9c54ed7cae610b39a34b36dce41801628.png",
        "title": "动物门诊",
        "address": "东光府前大街与邮政路交叉口南",
        "lowestprice": 0.0,
        "avgprice": 0.0,
        "latitude": 37.886136,
        "longitude": 116.545053,
        "showType": "easylife",
        "avgscore": 0.0,
        "comments": 0,
        "historyCouponCount": 0,
        "backCateName": "宠物医院",
        "areaname": "东光",
        "tag": [],
        "cate": [
          3,
          20691
        ],
        "recentScreen": null,
        "abstracts": [],
        "dangleAbstracts": null,
        "titleTags": [],
        "iUrl": null,
        "deals": null,
        "posdescr": null,
        "ct_poi": null,
        "trace": null,
        "landmarkDistance": null,
        "hasAds": false,
        "adsClickUrl": "",
        "adsShowUrl": "",
        "distance": "",
        "cityId": 127,
        "city": "沧州",
        "full": false
      },
      {
        "id": 167197356,
        "template": "pcfood",
        "imageUrl": "http://p0.meituan.net/w.h/ugcpic/9604b9c54ed7cae610b39a34b36dce41801628.png",
        "title": "麦萌宠物店",
        "address": "育才大街育才大街160号",
        "lowestprice": 0.0,
        "avgprice": 0.0,
        "latitude": 37.880083,
        "longitude": 116.547099,
        "showType": "easylife",
        "avgscore": 0.0,
        "comments": 0,
        "historyCouponCount": 0,
        "backCateName": "宠物店",
        "areaname": "育才大街",
        "tag": [],
        "cate": [
          3,
          20691,
          20630
        ],
        "recentScreen": null,
        "abstracts": [],
        "dangleAbstracts": null,
        "titleTags": [],
        "iUrl": null,
        "deals": null,
        "posdescr": null,
        "ct_poi": null,
        "trace": null,
        "landmarkDistance": null,
        "hasAds": false,
        "adsClickUrl": "",
        "adsShowUrl": "",
        "distance": "",
        "cityId": 0,
        "city": "",
        "full": false
      },
      {
        "id": 191895793,
        "template": "pcfood",
        "imageUrl": "http://p0.meituan.net/w.h/ugcpic/9604b9c54ed7cae610b39a34b36dce41801628.png",
        "title": "宠爱宠物店",
        "address": "东光东升路西100米",
        "lowestprice": 0.0,
        "avgprice": 0.0,
        "latitude": 37.890895,
        "longitude": 116.560976,
        "showType": "easylife",
        "avgscore": 0.0,
        "comments": 0,
        "historyCouponCount": 0,
        "backCateName": "宠物店",
        "areaname": "东光",
        "tag": [],
        "cate": [
          3,
          20691,
          20630
        ],
        "recentScreen": null,
        "abstracts": [],
        "dangleAbstracts": null,
        "titleTags": [],
        "iUrl": null,
        "deals": null,
        "posdescr": null,
        "ct_poi": null,
        "trace": null,
        "landmarkDistance": null,
        "hasAds": false,
        "adsClickUrl": "",
        "adsShowUrl": "",
        "distance": "",
        "cityId": 0,
        "city": "",
        "full": false
      },
      {
        "id": 114730078,
        "template": "pcfood",
        "imageUrl": "http://p0.meituan.net/w.h/ugcpic/9604b9c54ed7cae610b39a34b36dce41801628.png",
        "title": "104宠物店",
        "address": "东光火车站府前大街与观州路交叉口西南100米",
        "lowestprice": 0.0,
        "avgprice": 0.0,
        "latitude": 37.887994,
        "longitude": 116.531231,
        "showType": "easylife",
        "avgscore": 0.0,
        "comments": 0,
        "historyCouponCount": 0,
        "backCateName": "宠物店",
        "areaname": "东光火车站",
        "tag": [],
        "cate": [
          3,
          20691,
          20630
        ],
        "recentScreen": null,
        "abstracts": [],
        "dangleAbstracts": null,
        "titleTags": [],
        "iUrl": null,
        "deals": null,
        "posdescr": null,
        "ct_poi": null,
        "trace": null,
        "landmarkDistance": null,
        "hasAds": false,
        "adsClickUrl": "",
        "adsShowUrl": "",
        "distance": "",
        "cityId": 127,
        "city": "沧州",
        "full": false
      },
      {
        "id": 184228683,
        "template": "pcfood",
        "imageUrl": "http://p0.meituan.net/w.h/ugcpic/9604b9c54ed7cae610b39a34b36dce41801628.png",
        "title": "旺旺爱宠",
        "address": "建新路建新路193号附近",
        "lowestprice": 0.0,
        "avgprice": 0.0,
        "latitude": 37.886201,
        "longitude": 116.540498,
        "showType": "easylife",
        "avgscore": 0.0,
        "comments": 0,
        "historyCouponCount": 0,
        "backCateName": "宠物店",
        "areaname": "建新路",
        "tag": [],
        "cate": [
          3,
          20691,
          20630
        ],
        "recentScreen": null,
        "abstracts": [],
        "dangleAbstracts": null,
        "titleTags": [],
        "iUrl": null,
        "deals": null,
        "posdescr": null,
        "ct_poi": null,
        "trace": null,
        "landmarkDistance": null,
        "hasAds": false,
        "adsClickUrl": "",
        "adsShowUrl": "",
        "distance": "",
        "cityId": 0,
        "city": "",
        "full": false
      },
      {
        "id": 50732150,
        "template": "pcfood",
        "imageUrl": "http://p0.meituan.net/w.h/ugcpic/9604b9c54ed7cae610b39a34b36dce41801628.png",
        "title": "海龙水族馆",
        "address": "育才大街东兴路73号",
        "lowestprice": 0.0,
        "avgprice": 0.0,
        "latitude": 37.878056,
        "longitude": 116.548462,
        "showType": "easylife",
        "avgscore": 3.5,
        "comments": 0,
        "historyCouponCount": 0,
        "backCateName": "其他宠物",
        "areaname": "育才大街",
        "tag": [],
        "cate": [
          3,
          20691
        ],
        "recentScreen": null,
        "abstracts": [],
        "dangleAbstracts": null,
        "titleTags": [],
        "iUrl": null,
        "deals": null,
        "posdescr": null,
        "ct_poi": null,
        "trace": null,
        "landmarkDistance": null,
        "hasAds": false,
        "adsClickUrl": "",
        "adsShowUrl": "",
        "distance": "",
        "cityId": 127,
        "city": "沧州",
        "full": false
      },
      {
        "id": 93469980,
        "template": "pcfood",
        "imageUrl": "http://p0.meituan.net/w.h/ugcpic/9604b9c54ed7cae610b39a34b36dce41801628.png",
        "title": "宠爱有家",
        "address": "东光火车站府前大街与观州路交叉口旁",
        "lowestprice": 0.0,
        "avgprice": 0.0,
        "latitude": 37.888127,
        "longitude": 116.531256,
        "showType": "easylife",
        "avgscore": 0.0,
        "comments": 0,
        "historyCouponCount": 0,
        "backCateName": "宠物店",
        "areaname": "东光火车站",
        "tag": [],
        "cate": [
          3,
          20691,
          20630
        ],
        "recentScreen": null,
        "abstracts": [],
        "dangleAbstracts": null,
        "titleTags": [],
        "iUrl": null,
        "deals": null,
        "posdescr": null,
        "ct_poi": null,
        "trace": null,
        "landmarkDistance": null,
        "hasAds": false,
        "adsClickUrl": "",
        "adsShowUrl": "",
        "distance": "",
        "cityId": 127,
        "city": "沧州",
        "full": false
      },
      {
        "id": 167271668,
        "template": "pcfood",
        "imageUrl": "https://img.meituan.net/mogu/0818a95e3388f50bab1360bfaeed6a3d1141566.jpg",
        "title": "铭鲤阁",
        "address": "东光茧城大街14号",
        "lowestprice": 0.0,
        "avgprice": 0.0,
        "latitude": 37.886903,
        "longitude": 116.523718,
        "showType": "easylife",
        "avgscore": 0.0,
        "comments": 0,
        "historyCouponCount": 0,
        "backCateName": "其他宠物",
        "areaname": "东光",
        "tag": [],
        "cate": [
          3,
          20691
        ],
        "recentScreen": null,
        "abstracts": [],
        "dangleAbstracts": null,
        "titleTags": [],
        "iUrl": null,
        "deals": null,
        "posdescr": null,
        "ct_poi": null,
        "trace": null,
        "landmarkDistance": null,
        "hasAds": false,
        "adsClickUrl": "",
        "adsShowUrl": "",
        "distance": "",
        "cityId": 0,
        "city": "",
        "full": false
      },
      {
        "id": 167736353,
        "template": "pcfood",
        "imageUrl": "https://img.meituan.net/mogu/bed9158b80c5089a817fc23750a7515e748724.jpg",
        "title": "龙跃水族馆",
        "address": "东光东升路顺丰速运旁",
        "lowestprice": 0.0,
        "avgprice": 0.0,
        "latitude": 37.878303,
        "longitude": 116.553873,
        "showType": "easylife",
        "avgscore": 0.0,
        "comments": 0,
        "historyCouponCount": 0,
        "backCateName": "其他宠物",
        "areaname": "东光",
        "tag": [],
        "cate": [
          3,
          20691
        ],
        "recentScreen": null,
        "abstracts": [],
        "dangleAbstracts": null,
        "titleTags": [],
        "iUrl": null,
        "deals": null,
        "posdescr": null,
        "ct_poi": null,
        "trace": null,
        "landmarkDistance": null,
        "hasAds": false,
        "adsClickUrl": "",
        "adsShowUrl": "",
        "distance": "",
        "cityId": 0,
        "city": "",
        "full": false
      }
    ],
    "recommendResult": [
      {
        "id": 150460198,
        "template": "pcfood",
        "imageUrl": "http://qcloud.dpfile.com/pc/bBBNeVvopKwkwl35c6aEMNkyzqd3cPYJOz5CXw4EppB255s62df3gbRaguDlRD5BZSUjBikR5Ecy-DoGYkMhlg.jpg",
        "title": "中影众视影城（东光店）",
        "address": "东光迎宾大道东祥商场6层",
        "lowestprice": 19.9,
        "avgprice": 0.0,
        "latitude": 37.882667,
        "longitude": 116.552639,
        "showType": "cinema",
        "avgscore": 3.5,
        "comments": 0,
        "historyCouponCount": 43938,
        "backCateName": "电影院",
        "areaname": "东光",
        "tag": null,
        "cate": [
          99,
          20611,
          20632,
          20426
        ],
        "recentScreen": null,
        "abstracts": null,
        "dangleAbstracts": null,
        "titleTags": [],
        "iUrl": null,
        "deals": null,
        "posdescr": null,
        "ct_poi": null,
        "trace": null,
        "landmarkDistance": null,
        "hasAds": false,
        "adsClickUrl": "",
        "adsShowUrl": "",
        "distance": "",
        "cityId": 127,
        "city": "沧州",
        "full": false
      },
      {
        "id": 193676787,
        "template": "pcfood",
        "imageUrl": "https://img.meituan.net/w.h/msmerchant/ee9fc4a9a03c7b9ef867266c57557403170678.jpg",
        "title": "红辣椒火锅鸡",
        "address": "育才大街育才大街188号路北（蒙古烧烤龙虾隔壁）",
        "lowestprice": 66.6,
        "avgprice": 0.0,
        "latitude": 37.880846,
        "longitude": 116.545359,
        "showType": "food",
        "avgscore": 3.5,
        "comments": 6,
        "historyCouponCount": 20,
        "backCateName": "特色火锅",
        "areaname": "育才大街",
        "tag": null,
        "cate": [
          1,
          20632,
          20426,
          20557
        ],
        "recentScreen": null,
        "abstracts": null,
        "dangleAbstracts": [
          {
            "business": "买单",
            "dealId": -100,
            "icon": "https://p1.meituan.net/codeman/a43001c065622a9a9a5ef24ba9190c901262.png",
            "type": "pay",
            "message": "买单满200减15"
          }
        ],
        "titleTags": [
          "http://p0.meituan.net/codeman/a1af36edb271ae6ec74e36cde05d1ac8851.png"
        ],
        "iUrl": null,
        "deals": [
          {
            "id": 601102584,
            "title": "腿翅小份，建议2人使用，可免费使用包间",
            "subtitleA": null,
            "subtitleB": null,
            "subtitleC": null,
            "price": 66.6,
            "value": 115.0,
            "sales": 10.0,
            "iUrl": "",
            "stid": null,
            "trace": null,
            "tag": {
              "promotion": []
            }
          },
          {
            "id": 601105893,
            "title": "腿翅大份，建议3-4人使用，可免费使用包间",
            "subtitleA": null,
            "subtitleB": null,
            "subtitleC": null,
            "price": 99.8,
            "value": 150.0,
            "sales": 5.0,
            "iUrl": "",
            "stid": null,
            "trace": null,
            "tag": {
              "promotion": []
            }
          },
          {
            "id": 601102639,
            "title": "全鸡小份，建议2人使用，可免费使用包间",
            "subtitleA": null,
            "subtitleB": null,
            "subtitleC": null,
            "price": 66.6,
            "value": 115.0,
            "sales": 2.0,
            "iUrl": "",
            "stid": null,
            "trace": null,
            "tag": {
              "promotion": []
            }
          },
          {
            "id": 601111171,
            "title": "全鸡大份，建议3-4人使用，可免费使用包间",
            "subtitleA": null,
            "subtitleB": null,
            "subtitleC": null,
            "price": 86.6,
            "value": 135.0,
            "sales": 2.0,
            "iUrl": "",
            "stid": null,
            "trace": null,
            "tag": {
              "promotion": []
            }
          },
          {
            "id": 601742246,
            "title": "100元代金券1张，可叠加",
            "subtitleA": null,
            "subtitleB": null,
            "subtitleC": null,
            "price": 89.1,
            "value": 100.0,
            "sales": 1.0,
            "iUrl": "",
            "stid": null,
            "trace": null,
            "tag": {
              "promotion": []
            }
          }
        ],
        "posdescr": null,
        "ct_poi": null,
        "trace": null,
        "landmarkDistance": null,
        "hasAds": false,
        "adsClickUrl": "",
        "adsShowUrl": "",
        "distance": "",
        "cityId": 0,
        "city": "",
        "full": false
      },
      {
        "id": 157347022,
        "template": "pcfood",
        "imageUrl": "https://img.meituan.net/w.h/msmerchant/81d03f7ec3dea7d31d953114f8639618240597.jpg",
        "title": "大本家尚品烤肉主题餐厅",
        "address": "东光建设大街水木清华小区南门往东88木路北",
        "lowestprice": 68.0,
        "avgprice": 50.0,
        "latitude": 37.889446,
        "longitude": 116.55672,
        "showType": "food",
        "avgscore": 4.5,
        "comments": 379,
        "historyCouponCount": 2903,
        "backCateName": "韩式烤肉",
        "areaname": "东光",
        "tag": null,
        "cate": [
          1,
          20632,
          20426,
          20557
        ],
        "recentScreen": null,
        "abstracts": null,
        "dangleAbstracts": null,
        "titleTags": [],
        "iUrl": null,
        "deals": [
          {
            "id": 44610901,
            "title": "实惠四人餐，包间免费",
            "subtitleA": null,
            "subtitleB": null,
            "subtitleC": null,
            "price": 126.0,
            "value": 169.0,
            "sales": 1158.0,
            "iUrl": "",
            "stid": null,
            "trace": null,
            "tag": {
              "promotion": []
            }
          },
          {
            "id": 44610947,
            "title": "合家六人餐，包间免费",
            "subtitleA": null,
            "subtitleB": null,
            "subtitleC": null,
            "price": 216.0,
            "value": 266.0,
            "sales": 200.0,
            "iUrl": "",
            "stid": null,
            "trace": null,
            "tag": {
              "promotion": []
            }
          },
          {
            "id": 61100412,
            "title": "超值烤肉双人餐，包间免费",
            "subtitleA": null,
            "subtitleB": null,
            "subtitleC": null,
            "price": 68.0,
            "value": 109.0,
            "sales": 152.0,
            "iUrl": "",
            "stid": null,
            "trace": null,
            "tag": {
              "promotion": []
            }
          },
          {
            "id": 56833078,
            "title": "精品四人餐，包间免费",
            "subtitleA": null,
            "subtitleB": null,
            "subtitleC": null,
            "price": 159.0,
            "value": 219.0,
            "sales": 24.0,
            "iUrl": "",
            "stid": null,
            "trace": null,
            "tag": {
              "promotion": []
            }
          },
          {
            "id": 56950758,
            "title": "精品2人餐，包间免费",
            "subtitleA": null,
            "subtitleB": null,
            "subtitleC": null,
            "price": 108.0,
            "value": 157.0,
            "sales": 27.0,
            "iUrl": "",
            "stid": null,
            "trace": null,
            "tag": {
              "promotion": []
            }
          }
        ],
        "posdescr": null,
        "ct_poi": null,
        "trace": null,
        "landmarkDistance": null,
        "hasAds": false,
        "adsClickUrl": "",
        "adsShowUrl": "",
        "distance": "",
        "cityId": 127,
        "city": "沧州",
        "full": false
      },
      {
        "id": 4622654,
        "template": "pcfood",
        "imageUrl": "https://img.meituan.net/w.h/msmerchant/11e0cc9f806310db0398659a57fe4079110551.jpg",
        "title": "金麦利蛋糕面包",
        "address": "建新路茧城大街142号",
        "lowestprice": 1.99,
        "avgprice": 15.0,
        "latitude": 37.885579,
        "longitude": 116.540391,
        "showType": "food",
        "avgscore": 4.3,
        "comments": 292,
        "historyCouponCount": 7500,
        "backCateName": "蛋糕",
        "areaname": "建新路",
        "tag": null,
        "cate": [
          1,
          20426,
          20557
        ],
        "recentScreen": null,
        "abstracts": null,
        "dangleAbstracts": [
          {
            "business": "买单",
            "dealId": -101,
            "icon": "https://p1.meituan.net/codeman/a43001c065622a9a9a5ef24ba9190c901262.png",
            "type": "pay",
            "message": "买单9折"
          }
        ],
        "titleTags": [
          "http://p0.meituan.net/codeman/a1af36edb271ae6ec74e36cde05d1ac8851.png"
        ],
        "iUrl": null,
        "deals": [
          {
            "id": 34055849,
            "title": "30元代金券1张，全场通用，可叠加使用",
            "subtitleA": null,
            "subtitleB": null,
            "subtitleC": null,
            "price": 25.5,
            "value": 30.0,
            "sales": 308.0,
            "iUrl": "",
            "stid": null,
            "trace": null,
            "tag": {
              "promotion": []
            }
          },
          {
            "id": 34055846,
            "title": "50元代金券1张，全场通用，可叠加使用",
            "subtitleA": null,
            "subtitleB": null,
            "subtitleC": null,
            "price": 42.5,
            "value": 50.0,
            "sales": 310.0,
            "iUrl": "",
            "stid": null,
            "trace": null,
            "tag": {
              "promotion": []
            }
          },
          {
            "id": 55042434,
            "title": "乳脂草莓蛋糕1个，约8英寸，圆",
            "subtitleA": null,
            "subtitleB": null,
            "subtitleC": null,
            "price": 75.0,
            "value": 88.0,
            "sales": 27.0,
            "iUrl": "",
            "stid": null,
            "trace": null,
            "tag": {
              "promotion": []
            }
          },
          {
            "id": 55042374,
            "title": "十寸布朗熊蛋糕1个，约10英寸，圆",
            "subtitleA": null,
            "subtitleB": null,
            "subtitleC": null,
            "price": 109.0,
            "value": 129.0,
            "sales": 8.0,
            "iUrl": "",
            "stid": null,
            "trace": null,
            "tag": {
              "promotion": []
            }
          },
          {
            "id": 55042470,
            "title": "8寸奥利奥蛋糕1个，约8英寸，圆",
            "subtitleA": null,
            "subtitleB": null,
            "subtitleC": null,
            "price": 85.0,
            "value": 98.0,
            "sales": 0.0,
            "iUrl": "",
            "stid": null,
            "trace": null,
            "tag": {
              "promotion": []
            }
          }
        ],
        "posdescr": null,
        "ct_poi": null,
        "trace": null,
        "landmarkDistance": null,
        "hasAds": false,
        "adsClickUrl": "",
        "adsShowUrl": "",
        "distance": "",
        "cityId": 127,
        "city": "沧州",
        "full": false
      },
      {
        "id": 69966547,
        "template": "pcfood",
        "imageUrl": "https://img.meituan.net/w.h/msmerchant/e2d0aeedd521b82a2a1577c5943c06971870278.jpg",
        "title": "千水鱼火锅",
        "address": "东光东祥商厦南200米路西",
        "lowestprice": 42.0,
        "avgprice": 19.0,
        "latitude": 37.881216,
        "longitude": 116.550626,
        "showType": "food",
        "avgscore": 4.2,
        "comments": 691,
        "historyCouponCount": 4757,
        "backCateName": "鱼火锅",
        "areaname": "东光",
        "tag": null,
        "cate": [
          1,
          20632,
          20426
        ],
        "recentScreen": null,
        "abstracts": null,
        "dangleAbstracts": null,
        "titleTags": [],
        "iUrl": null,
        "deals": [
          {
            "id": 54964668,
            "title": "香辣草鱼锅，建议2-3人使用",
            "subtitleA": null,
            "subtitleB": null,
            "subtitleC": null,
            "price": 47.0,
            "value": 75.0,
            "sales": 125.0,
            "iUrl": "",
            "stid": null,
            "trace": null,
            "tag": {
              "promotion": []
            }
          },
          {
            "id": 54964875,
            "title": "鲶鱼火锅，建议2-3人使用",
            "subtitleA": null,
            "subtitleB": null,
            "subtitleC": null,
            "price": 42.0,
            "value": 70.0,
            "sales": 79.0,
            "iUrl": "",
            "stid": null,
            "trace": null,
            "tag": {
              "promotion": []
            }
          },
          {
            "id": 54965036,
            "title": "香辣草鱼锅，建议4-6人使用",
            "subtitleA": null,
            "subtitleB": null,
            "subtitleC": null,
            "price": 68.0,
            "value": 99.0,
            "sales": 35.0,
            "iUrl": "",
            "stid": null,
            "trace": null,
            "tag": {
              "promotion": []
            }
          },
          {
            "id": 54965140,
            "title": "酸菜鱼火锅，建议6-8人使用",
            "subtitleA": null,
            "subtitleB": null,
            "subtitleC": null,
            "price": 88.0,
            "value": 119.0,
            "sales": 20.0,
            "iUrl": "",
            "stid": null,
            "trace": null,
            "tag": {
              "promotion": []
            }
          },
          {
            "id": 54965089,
            "title": "酸菜鱼酸菜鱼火锅，建议4-6人使用",
            "subtitleA": null,
            "subtitleB": null,
            "subtitleC": null,
            "price": 68.0,
            "value": 99.0,
            "sales": 64.0,
            "iUrl": "",
            "stid": null,
            "trace": null,
            "tag": {
              "promotion": []
            }
          }
        ],
        "posdescr": null,
        "ct_poi": null,
        "trace": null,
        "landmarkDistance": null,
        "hasAds": false,
        "adsClickUrl": "",
        "adsShowUrl": "",
        "distance": "",
        "cityId": 127,
        "city": "沧州",
        "full": false
      },
      {
        "id": 42623496,
        "template": "pcfood",
        "imageUrl": "http://p0.meituan.net/w.h/deal/8d947efa3574b58c6900a7b5b793e83d25767.jpg",
        "title": "好滋味快餐连锁店（东光店）",
        "address": "东光华联凤凰城2号楼206号门市楼",
        "lowestprice": 12.6,
        "avgprice": 20.0,
        "latitude": 37.882501,
        "longitude": 116.558634,
        "showType": "food",
        "avgscore": 3.0,
        "comments": 4,
        "historyCouponCount": 46,
        "backCateName": "快餐",
        "areaname": "东光",
        "tag": null,
        "cate": [
          1,
          20426,
          20557
        ],
        "recentScreen": null,
        "abstracts": null,
        "dangleAbstracts": null,
        "titleTags": [],
        "iUrl": null,
        "deals": [
          {
            "id": 45159243,
            "title": "单人套餐，包间免费",
            "subtitleA": null,
            "subtitleB": null,
            "subtitleC": null,
            "price": 12.6,
            "value": 15.0,
            "sales": 50.0,
            "iUrl": "",
            "stid": null,
            "trace": null,
            "tag": {
              "promotion": []
            }
          },
          {
            "id": 45158652,
            "title": "超值套餐，建议2-3人使用",
            "subtitleA": null,
            "subtitleB": null,
            "subtitleC": null,
            "price": 38.6,
            "value": 43.0,
            "sales": 9.0,
            "iUrl": "",
            "stid": null,
            "trace": null,
            "tag": {
              "promotion": []
            }
          },
          {
            "id": 45159053,
            "title": "超值套餐，建议2-3人使用",
            "subtitleA": null,
            "subtitleB": null,
            "subtitleC": null,
            "price": 44.6,
            "value": 52.0,
            "sales": 0.0,
            "iUrl": "",
            "stid": null,
            "trace": null,
            "tag": {
              "promotion": []
            }
          }
        ],
        "posdescr": null,
        "ct_poi": null,
        "trace": null,
        "landmarkDistance": null,
        "hasAds": false,
        "adsClickUrl": "",
        "adsShowUrl": "",
        "distance": "",
        "cityId": 127,
        "city": "沧州",
        "full": false
      },
      {
        "id": 42703239,
        "template": "pcfood",
        "imageUrl": "http://p0.meituan.net/w.h/deal/ac360174fee80a0476c1d184a6632baf311722.jpg",
        "title": "绿麦量贩式KTV",
        "address": "东光迎宾大道金地广场五楼",
        "lowestprice": 39.9,
        "avgprice": 0.0,
        "latitude": 37.881836,
        "longitude": 116.560258,
        "showType": "ktv",
        "avgscore": 4.9,
        "comments": 1681,
        "historyCouponCount": 9878,
        "backCateName": "量贩式KTV",
        "areaname": "东光",
        "tag": null,
        "cate": [
          2,
          20611,
          20632,
          20426
        ],
        "recentScreen": null,
        "abstracts": null,
        "dangleAbstracts": null,
        "titleTags": [],
        "iUrl": null,
        "deals": [
          {
            "id": 47414264,
            "title": "阳光场小包3小时欢唱+美食套餐",
            "subtitleA": null,
            "subtitleB": null,
            "subtitleC": null,
            "price": 39.9,
            "value": 148.0,
            "sales": 1620.0,
            "iUrl": "",
            "stid": null,
            "trace": null,
            "tag": {
              "promotion": []
            }
          },
          {
            "id": 47414259,
            "title": "阳光场中包3小时欢唱+美食套餐",
            "subtitleA": null,
            "subtitleB": null,
            "subtitleC": null,
            "price": 49.9,
            "value": 178.0,
            "sales": 550.0,
            "iUrl": "",
            "stid": null,
            "trace": null,
            "tag": {
              "promotion": []
            }
          },
          {
            "id": 47414269,
            "title": "阳光场大包3小时欢唱+美食套餐",
            "subtitleA": null,
            "subtitleB": null,
            "subtitleC": null,
            "price": 59.9,
            "value": 208.0,
            "sales": 191.0,
            "iUrl": "",
            "stid": null,
            "trace": null,
            "tag": {
              "promotion": []
            }
          },
          {
            "id": 55391661,
            "title": "啤酒套餐（不含欢唱）",
            "subtitleA": null,
            "subtitleB": null,
            "subtitleC": null,
            "price": 98.0,
            "value": 158.0,
            "sales": 44.0,
            "iUrl": "",
            "stid": null,
            "trace": null,
            "tag": {
              "promotion": []
            }
          },
          {
            "id": 55391669,
            "title": "红酒套餐（不含欢唱）",
            "subtitleA": null,
            "subtitleB": null,
            "subtitleC": null,
            "price": 108.0,
            "value": 208.0,
            "sales": 7.0,
            "iUrl": "",
            "stid": null,
            "trace": null,
            "tag": {
              "promotion": []
            }
          }
        ],
        "posdescr": null,
        "ct_poi": null,
        "trace": null,
        "landmarkDistance": null,
        "hasAds": false,
        "adsClickUrl": "",
        "adsShowUrl": "",
        "distance": "",
        "cityId": 127,
        "city": "沧州",
        "full": false
      },
      {
        "id": 119448949,
        "template": "pcfood",
        "imageUrl": "http://p0.meituan.net/w.h/waimaipoi/5c5f1e3913a8e7f09777fd38d33a31e6205130.jpg",
        "title": "魔法私厨披萨",
        "address": "东光建设大街世纪嘉园小区10号楼1号门市",
        "lowestprice": 0.0,
        "avgprice": 0.0,
        "latitude": 37.891345,
        "longitude": 116.549678,
        "showType": "food",
        "avgscore": 0.0,
        "comments": 0,
        "historyCouponCount": 0,
        "backCateName": "披萨",
        "areaname": "东光",
        "tag": null,
        "cate": [
          1,
          20632,
          20426,
          20557
        ],
        "recentScreen": null,
        "abstracts": null,
        "dangleAbstracts": null,
        "titleTags": [
          "http://p0.meituan.net/codeman/a1af36edb271ae6ec74e36cde05d1ac8851.png"
        ],
        "iUrl": null,
        "deals": null,
        "posdescr": null,
        "ct_poi": null,
        "trace": null,
        "landmarkDistance": null,
        "hasAds": false,
        "adsClickUrl": "",
        "adsShowUrl": "",
        "distance": "",
        "cityId": 127,
        "city": "沧州",
        "full": false
      },
      {
        "id": 41535215,
        "template": "pcfood",
        "imageUrl": "https://img.meituan.net/w.h/msmerchant/014d7703767a9d452f4243296bec764a258438.jpg",
        "title": "肯德基（东光店）",
        "address": "东光东升路东侧茧城大街以北华联购物广场一层",
        "lowestprice": 5.4,
        "avgprice": 30.0,
        "latitude": 37.882595,
        "longitude": 116.55649,
        "showType": "food",
        "avgscore": 4.0,
        "comments": 0,
        "historyCouponCount": 0,
        "backCateName": "快餐",
        "areaname": "东光",
        "tag": null,
        "cate": [
          1,
          20426,
          20557
        ],
        "recentScreen": null,
        "abstracts": null,
        "dangleAbstracts": null,
        "titleTags": [],
        "iUrl": null,
        "deals": [
          {
            "id": 54437787,
            "title": "20元代金券1张，可叠加",
            "subtitleA": null,
            "subtitleB": null,
            "subtitleC": null,
            "price": 19.0,
            "value": 20.0,
            "sales": 364005.0,
            "iUrl": "",
            "stid": null,
            "trace": null,
            "tag": {
              "promotion": []
            }
          },
          {
            "id": 59129366,
            "title": "【热销汉堡】新奥尔良烤鸡腿堡1份",
            "subtitleA": null,
            "subtitleB": null,
            "subtitleC": null,
            "price": 16.2,
            "value": 18.0,
            "sales": 339878.0,
            "iUrl": "",
            "stid": null,
            "trace": null,
            "tag": {
              "promotion": []
            }
          },
          {
            "id": 59497154,
            "title": "原味花筒1份，提供免费WiFi",
            "subtitleA": null,
            "subtitleB": null,
            "subtitleC": null,
            "price": 5.4,
            "value": 6.0,
            "sales": 191653.0,
            "iUrl": "",
            "stid": null,
            "trace": null,
            "tag": {
              "promotion": []
            }
          },
          {
            "id": 54438280,
            "title": "50元代金券1张，可叠加",
            "subtitleA": null,
            "subtitleB": null,
            "subtitleC": null,
            "price": 47.5,
            "value": 50.0,
            "sales": 103240.0,
            "iUrl": "",
            "stid": null,
            "trace": null,
            "tag": {
              "promotion": []
            }
          },
          {
            "id": 59490184,
            "title": "吮指原味鸡1份，提供免费WiFi",
            "subtitleA": null,
            "subtitleB": null,
            "subtitleC": null,
            "price": 9.45,
            "value": 10.5,
            "sales": 106716.0,
            "iUrl": "",
            "stid": null,
            "trace": null,
            "tag": {
              "promotion": []
            }
          }
        ],
        "posdescr": null,
        "ct_poi": null,
        "trace": null,
        "landmarkDistance": null,
        "hasAds": false,
        "adsClickUrl": "",
        "adsShowUrl": "",
        "distance": "",
        "cityId": 127,
        "city": "沧州",
        "full": false
      },
      {
        "id": 115363772,
        "template": "pcfood",
        "imageUrl": "http://p0.meituan.net/w.h/deal/954b2de4c46e2c64b7b60252a5fd1484193596.jpg",
        "title": "广州味道烘培体验店",
        "address": "建新路建新路与茧城大街交叉口南120米",
        "lowestprice": 8.0,
        "avgprice": 20.0,
        "latitude": 37.884022,
        "longitude": 116.54035,
        "showType": "food",
        "avgscore": 4.0,
        "comments": 9,
        "historyCouponCount": 196,
        "backCateName": "甜点饮品",
        "areaname": "建新路",
        "tag": null,
        "cate": [
          1,
          20426,
          20557
        ],
        "recentScreen": null,
        "abstracts": null,
        "dangleAbstracts": null,
        "titleTags": [],
        "iUrl": null,
        "deals": [
          {
            "id": 29033321,
            "title": "4寸水果蛋糕1份",
            "subtitleA": null,
            "subtitleB": null,
            "subtitleC": null,
            "price": 8.0,
            "value": 10.0,
            "sales": 1031.0,
            "iUrl": "",
            "stid": null,
            "trace": null,
            "tag": {
              "promotion": []
            }
          },
          {
            "id": 29033306,
            "title": "乳脂奶油水果蛋糕1个，约8英寸，圆",
            "subtitleA": null,
            "subtitleB": null,
            "subtitleC": null,
            "price": 68.0,
            "value": 88.0,
            "sales": 989.0,
            "iUrl": "",
            "stid": null,
            "trace": null,
            "tag": {
              "promotion": []
            }
          },
          {
            "id": 29033336,
            "title": "乳脂奶油水果蛋糕1个，约12英寸，圆",
            "subtitleA": null,
            "subtitleB": null,
            "subtitleC": null,
            "price": 128.0,
            "value": 158.0,
            "sales": 409.0,
            "iUrl": "",
            "stid": null,
            "trace": null,
            "tag": {
              "promotion": []
            }
          },
          {
            "id": 29033313,
            "title": "乳脂奶油水果蛋糕1个，约10英寸，圆",
            "subtitleA": null,
            "subtitleB": null,
            "subtitleC": null,
            "price": 108.0,
            "value": 118.0,
            "sales": 321.0,
            "iUrl": "",
            "stid": null,
            "trace": null,
            "tag": {
              "promotion": []
            }
          },
          {
            "id": 29022140,
            "title": "数码蛋糕1个，约10英寸，圆",
            "subtitleA": null,
            "subtitleB": null,
            "subtitleC": null,
            "price": 128.0,
            "value": 168.0,
            "sales": 7.0,
            "iUrl": "",
            "stid": null,
            "trace": null,
            "tag": {
              "promotion": []
            }
          }
        ],
        "posdescr": null,
        "ct_poi": null,
        "trace": null,
        "landmarkDistance": null,
        "hasAds": false,
        "adsClickUrl": "",
        "adsShowUrl": "",
        "distance": "",
        "cityId": 127,
        "city": "沧州",
        "full": false
      },
      {
        "id": 80700261,
        "template": "pcfood",
        "imageUrl": "http://p1.meituan.net/w.h/mogu/437a2c65f14f232f632a7c416e2e82a5238081.jpg",
        "title": "稻草人永和豆浆",
        "address": "东光东光信誉楼商厦1层",
        "lowestprice": 5.9,
        "avgprice": 5.0,
        "latitude": 37.872415,
        "longitude": 116.545312,
        "showType": "food",
        "avgscore": 3.9,
        "comments": 226,
        "historyCouponCount": 1959,
        "backCateName": "快餐",
        "areaname": "东光",
        "tag": null,
        "cate": [
          1,
          20426,
          20557
        ],
        "recentScreen": null,
        "abstracts": null,
        "dangleAbstracts": null,
        "titleTags": [],
        "iUrl": null,
        "deals": [
          {
            "id": 36069995,
            "title": "小笼包套餐，建议单人使用",
            "subtitleA": null,
            "subtitleB": null,
            "subtitleC": null,
            "price": 11.9,
            "value": 18.0,
            "sales": 156.0,
            "iUrl": "",
            "stid": null,
            "trace": null,
            "tag": {
              "promotion": []
            }
          },
          {
            "id": 36069946,
            "title": "西红柿鸡蛋饭，建议单人使用",
            "subtitleA": null,
            "subtitleB": null,
            "subtitleC": null,
            "price": 15.0,
            "value": 20.0,
            "sales": 84.0,
            "iUrl": "",
            "stid": null,
            "trace": null,
            "tag": {
              "promotion": []
            }
          },
          {
            "id": 36070313,
            "title": "鱼香肉丝，建议单人使用，包间免费",
            "subtitleA": null,
            "subtitleB": null,
            "subtitleC": null,
            "price": 17.9,
            "value": 24.0,
            "sales": 59.0,
            "iUrl": "",
            "stid": null,
            "trace": null,
            "tag": {
              "promotion": []
            }
          },
          {
            "id": 36070243,
            "title": "狮子头or卤肉饭，建议单人使用",
            "subtitleA": null,
            "subtitleB": null,
            "subtitleC": null,
            "price": 19.9,
            "value": 28.0,
            "sales": 58.0,
            "iUrl": "",
            "stid": null,
            "trace": null,
            "tag": {
              "promotion": []
            }
          },
          {
            "id": 36069873,
            "title": "油条+豆浆，建议单人使用",
            "subtitleA": null,
            "subtitleB": null,
            "subtitleC": null,
            "price": 5.9,
            "value": 8.0,
            "sales": 54.0,
            "iUrl": "",
            "stid": null,
            "trace": null,
            "tag": {
              "promotion": []
            }
          }
        ],
        "posdescr": null,
        "ct_poi": null,
        "trace": null,
        "landmarkDistance": null,
        "hasAds": false,
        "adsClickUrl": "",
        "adsShowUrl": "",
        "distance": "",
        "cityId": 127,
        "city": "沧州",
        "full": false
      },
      {
        "id": 79805936,
        "template": "pcfood",
        "imageUrl": "http://p1.meituan.net/w.h/deal/8f6ff079696d2ab80c4ec099296d1a5361908.jpg",
        "title": "张扬米线",
        "address": "建新路建新路124号",
        "lowestprice": 17.0,
        "avgprice": 10.0,
        "latitude": 37.88634,
        "longitude": 116.5406,
        "showType": "food",
        "avgscore": 5.0,
        "comments": 81,
        "historyCouponCount": 362,
        "backCateName": "小吃快餐",
        "areaname": "建新路",
        "tag": null,
        "cate": [
          1,
          20426,
          20557
        ],
        "recentScreen": null,
        "abstracts": null,
        "dangleAbstracts": null,
        "titleTags": [],
        "iUrl": null,
        "deals": [
          {
            "id": 37153633,
            "title": "双人标准餐，提供免费WiFi",
            "subtitleA": null,
            "subtitleB": null,
            "subtitleC": null,
            "price": 19.9,
            "value": 29.0,
            "sales": 303.0,
            "iUrl": "",
            "stid": null,
            "trace": null,
            "tag": {
              "promotion": []
            }
          },
          {
            "id": 37153623,
            "title": "单人豪华套餐，提供免费WiFi",
            "subtitleA": null,
            "subtitleB": null,
            "subtitleC": null,
            "price": 17.0,
            "value": 23.0,
            "sales": 39.0,
            "iUrl": "",
            "stid": null,
            "trace": null,
            "tag": {
              "promotion": []
            }
          },
          {
            "id": 37153603,
            "title": "双人套餐，提供免费WiFi",
            "subtitleA": null,
            "subtitleB": null,
            "subtitleC": null,
            "price": 39.9,
            "value": 53.0,
            "sales": 8.0,
            "iUrl": "",
            "stid": null,
            "trace": null,
            "tag": {
              "promotion": []
            }
          },
          {
            "id": 33406145,
            "title": "情侣套餐，提供免费WiFi",
            "subtitleA": null,
            "subtitleB": null,
            "subtitleC": null,
            "price": 37.8,
            "value": 47.0,
            "sales": 5.0,
            "iUrl": "",
            "stid": null,
            "trace": null,
            "tag": {
              "promotion": []
            }
          }
        ],
        "posdescr": null,
        "ct_poi": null,
        "trace": null,
        "landmarkDistance": null,
        "hasAds": false,
        "adsClickUrl": "",
        "adsShowUrl": "",
        "distance": "",
        "cityId": 127,
        "city": "沧州",
        "full": false
      },
      {
        "id": 4659518,
        "template": "pcfood",
        "imageUrl": "http://p0.meituan.net/w.h/deal/b8a8f2542b235d64761be24e12fd839c237583.jpg",
        "title": "麦德基（东光店）",
        "address": "建新路建新路南段安居小区北门",
        "lowestprice": 3.9,
        "avgprice": 20.0,
        "latitude": 37.883738,
        "longitude": 116.540311,
        "showType": "food",
        "avgscore": 3.9,
        "comments": 561,
        "historyCouponCount": 3916,
        "backCateName": "快餐",
        "areaname": "建新路",
        "tag": null,
        "cate": [
          1,
          20426,
          20557
        ],
        "recentScreen": null,
        "abstracts": null,
        "dangleAbstracts": null,
        "titleTags": [],
        "iUrl": null,
        "deals": [
          {
            "id": 31260484,
            "title": "内容2选1，提供免费WiFi",
            "subtitleA": null,
            "subtitleB": null,
            "subtitleC": null,
            "price": 7.9,
            "value": 10.0,
            "sales": 1946.0,
            "iUrl": "",
            "stid": null,
            "trace": null,
            "tag": {
              "promotion": []
            }
          },
          {
            "id": 35501080,
            "title": "麦香鸡腿堡A套餐1份",
            "subtitleA": null,
            "subtitleB": null,
            "subtitleC": null,
            "price": 12.9,
            "value": 15.0,
            "sales": 706.0,
            "iUrl": "",
            "stid": null,
            "trace": null,
            "tag": {
              "promotion": []
            }
          },
          {
            "id": 31260470,
            "title": "内容2选1，提供免费WiFi",
            "subtitleA": null,
            "subtitleB": null,
            "subtitleC": null,
            "price": 3.9,
            "value": 6.0,
            "sales": 379.0,
            "iUrl": "",
            "stid": null,
            "trace": null,
            "tag": {
              "promotion": []
            }
          }
        ],
        "posdescr": null,
        "ct_poi": null,
        "trace": null,
        "landmarkDistance": null,
        "hasAds": false,
        "adsClickUrl": "",
        "adsShowUrl": "",
        "distance": "",
        "cityId": 127,
        "city": "沧州",
        "full": false
      },
      {
        "id": 159527794,
        "template": "pcfood",
        "imageUrl": "http://p1.meituan.net/w.h/mogu/7540986307dd93d7b578e248ffc309ac508793.jpg",
        "title": "遇见你之前",
        "address": "东光迎宾大道与东升路交叉口东南角（信和商厦对面）",
        "lowestprice": 19.9,
        "avgprice": 36.0,
        "latitude": 37.882031,
        "longitude": 116.556272,
        "showType": "food",
        "avgscore": 3.7,
        "comments": 49,
        "historyCouponCount": 361,
        "backCateName": "俄罗斯菜",
        "areaname": "东光",
        "tag": null,
        "cate": [
          1,
          20632,
          20426,
          20557
        ],
        "recentScreen": null,
        "abstracts": null,
        "dangleAbstracts": null,
        "titleTags": [],
        "iUrl": null,
        "deals": [
          {
            "id": 51241030,
            "title": "情侣套餐，有赠品，包间免费",
            "subtitleA": null,
            "subtitleB": null,
            "subtitleC": null,
            "price": 131.4,
            "value": 188.0,
            "sales": 20.0,
            "iUrl": "",
            "stid": null,
            "trace": null,
            "tag": {
              "promotion": []
            }
          },
          {
            "id": 49183715,
            "title": "温馨双人餐，有赠品，包间免费",
            "subtitleA": null,
            "subtitleB": null,
            "subtitleC": null,
            "price": 98.0,
            "value": 112.0,
            "sales": 12.0,
            "iUrl": "",
            "stid": null,
            "trace": null,
            "tag": {
              "promotion": []
            }
          },
          {
            "id": 51240708,
            "title": "牛排单人套餐，有赠品，包间免费",
            "subtitleA": null,
            "subtitleB": null,
            "subtitleC": null,
            "price": 46.0,
            "value": 51.0,
            "sales": 1.0,
            "iUrl": "",
            "stid": null,
            "trace": null,
            "tag": {
              "promotion": []
            }
          },
          {
            "id": 54787635,
            "title": "汉堡套餐，建议单人使用，有赠品",
            "subtitleA": null,
            "subtitleB": null,
            "subtitleC": null,
            "price": 19.9,
            "value": 30.0,
            "sales": 1.0,
            "iUrl": "",
            "stid": null,
            "trace": null,
            "tag": {
              "promotion": []
            }
          }
        ],
        "posdescr": null,
        "ct_poi": null,
        "trace": null,
        "landmarkDistance": null,
        "hasAds": false,
        "adsClickUrl": "",
        "adsShowUrl": "",
        "distance": "",
        "cityId": 127,
        "city": "沧州",
        "full": false
      },
      {
        "id": 5691177,
        "template": "pcfood",
        "imageUrl": "https://img.meituan.net/w.h/msmerchant/9e2a97f4835f0473bb3284323d8d12332695498.jpg",
        "title": "好再来蛋糕房",
        "address": "东光火车站中兴路70号",
        "lowestprice": 1.2,
        "avgprice": 11.0,
        "latitude": 37.88523,
        "longitude": 116.53541,
        "showType": "food",
        "avgscore": 5.0,
        "comments": 1331,
        "historyCouponCount": 15046,
        "backCateName": "甜点饮品",
        "areaname": "东光火车站",
        "tag": null,
        "cate": [
          1,
          20426,
          20557
        ],
        "recentScreen": null,
        "abstracts": null,
        "dangleAbstracts": null,
        "titleTags": [],
        "iUrl": null,
        "deals": [
          {
            "id": 30201996,
            "title": "蛋挞1个",
            "subtitleA": null,
            "subtitleB": null,
            "subtitleC": null,
            "price": 1.2,
            "value": 3.0,
            "sales": 11313.0,
            "iUrl": "",
            "stid": null,
            "trace": null,
            "tag": {
              "promotion": []
            }
          }
        ],
        "posdescr": null,
        "ct_poi": null,
        "trace": null,
        "landmarkDistance": null,
        "hasAds": false,
        "adsClickUrl": "",
        "adsShowUrl": "",
        "distance": "",
        "cityId": 127,
        "city": "沧州",
        "full": false
      },
      {
        "id": 195533048,
        "template": "pcfood",
        "imageUrl": "http://p0.meituan.net/mogu/47c933076ac4b8e6674f99fc8819b46a958156.jpg",
        "title": "大街小巷民谣音乐餐厅",
        "address": "东光致远街与建新路交叉口东南角",
        "lowestprice": 0.0,
        "avgprice": 0.0,
        "latitude": 37.898,
        "longitude": 116.54403,
        "showType": "food",
        "avgscore": 3.5,
        "comments": 0,
        "historyCouponCount": 0,
        "backCateName": "歌舞表演餐厅",
        "areaname": "东光",
        "tag": null,
        "cate": [
          1,
          20632,
          20426,
          20557
        ],
        "recentScreen": null,
        "abstracts": null,
        "dangleAbstracts": null,
        "titleTags": [],
        "iUrl": null,
        "deals": null,
        "posdescr": null,
        "ct_poi": null,
        "trace": null,
        "landmarkDistance": null,
        "hasAds": false,
        "adsClickUrl": "",
        "adsShowUrl": "",
        "distance": "",
        "cityId": 0,
        "city": "",
        "full": false
      },
      {
        "id": 159203494,
        "template": "pcfood",
        "imageUrl": "http://p1.meituan.net/w.h/merchantpic/9b14258505aba493d45fe73849c0734220030.png",
        "title": "正新鸡排",
        "address": "建新路建新路173号",
        "lowestprice": 0.0,
        "avgprice": 15.0,
        "latitude": 37.88501,
        "longitude": 116.5407,
        "showType": "food",
        "avgscore": 4.0,
        "comments": 0,
        "historyCouponCount": 0,
        "backCateName": "小吃快餐",
        "areaname": "建新路",
        "tag": null,
        "cate": [
          1,
          20426,
          20557
        ],
        "recentScreen": null,
        "abstracts": null,
        "dangleAbstracts": null,
        "titleTags": [],
        "iUrl": null,
        "deals": null,
        "posdescr": null,
        "ct_poi": null,
        "trace": null,
        "landmarkDistance": null,
        "hasAds": false,
        "adsClickUrl": "",
        "adsShowUrl": "",
        "distance": "",
        "cityId": 127,
        "city": "沧州",
        "full": false
      },
      {
        "id": 177949897,
        "template": "pcfood",
        "imageUrl": "http://p1.meituan.net/w.h/merchantpic/52b141fa0d65063d2d435a5cdb426915359898.jpg",
        "title": "麦当劳（东光东兴路店）",
        "address": "东光东兴路西侧普照大街北侧信誉楼商厦1层",
        "lowestprice": 0.0,
        "avgprice": 20.0,
        "latitude": 37.872299,
        "longitude": 116.545469,
        "showType": "food",
        "avgscore": 4.5,
        "comments": 0,
        "historyCouponCount": 0,
        "backCateName": "快餐",
        "areaname": "东光",
        "tag": null,
        "cate": [
          1,
          20426,
          20557
        ],
        "recentScreen": null,
        "abstracts": null,
        "dangleAbstracts": null,
        "titleTags": [],
        "iUrl": null,
        "deals": null,
        "posdescr": null,
        "ct_poi": null,
        "trace": null,
        "landmarkDistance": null,
        "hasAds": false,
        "adsClickUrl": "",
        "adsShowUrl": "",
        "distance": "",
        "cityId": 127,
        "city": "沧州",
        "full": false
      },
      {
        "id": 96121275,
        "template": "pcfood",
        "imageUrl": "http://p1.meituan.net/w.h/mogu/fde18451f1855caf837f94711218398554448.jpg",
        "title": "微利家常菜",
        "address": "东光建新路与建设大街交叉口东50米",
        "lowestprice": 0.0,
        "avgprice": 8.0,
        "latitude": 37.89071,
        "longitude": 116.54222,
        "showType": "food",
        "avgscore": 3.5,
        "comments": 0,
        "historyCouponCount": 0,
        "backCateName": "家常菜",
        "areaname": "东光",
        "tag": null,
        "cate": [
          1,
          20632,
          20426,
          20557
        ],
        "recentScreen": null,
        "abstracts": null,
        "dangleAbstracts": null,
        "titleTags": [],
        "iUrl": null,
        "deals": null,
        "posdescr": null,
        "ct_poi": null,
        "trace": null,
        "landmarkDistance": null,
        "hasAds": false,
        "adsClickUrl": "",
        "adsShowUrl": "",
        "distance": "",
        "cityId": 0,
        "city": "",
        "full": false
      },
      {
        "id": 188464900,
        "template": "pcfood",
        "imageUrl": "http://qcloud.dpfile.com/pc/kAMGKeb0ieWH5brZhfGNp4EOG8OZMWZVUmamQTYgepTDHt9ll3OGTUOUsaA008sMZSUjBikR5Ecy-DoGYkMhlg.jpg",
        "title": "蜀一蜀二（东光店）",
        "address": "育才大街育才大街东首路南",
        "lowestprice": 0.0,
        "avgprice": 0.0,
        "latitude": 37.879371,
        "longitude": 116.551406,
        "showType": "food",
        "avgscore": 0.0,
        "comments": 0,
        "historyCouponCount": 0,
        "backCateName": "川菜",
        "areaname": "育才大街",
        "tag": null,
        "cate": [
          1,
          20632,
          20426,
          20557
        ],
        "recentScreen": null,
        "abstracts": null,
        "dangleAbstracts": null,
        "titleTags": [],
        "iUrl": null,
        "deals": null,
        "posdescr": null,
        "ct_poi": null,
        "trace": null,
        "landmarkDistance": null,
        "hasAds": false,
        "adsClickUrl": "",
        "adsShowUrl": "",
        "distance": "",
        "cityId": 127,
        "city": "沧州",
        "full": false
      },
      {
        "id": 52045401,
        "template": "pcfood",
        "imageUrl": "http://p1.meituan.net/w.h/poi/fadd7a68de39f65e10f505ed2d78d684104448.jpg",
        "title": "老边饺子馆",
        "address": "府前大街东光镇府前大街245号",
        "lowestprice": 0.0,
        "avgprice": 35.0,
        "latitude": 37.886352,
        "longitude": 116.556984,
        "showType": "food",
        "avgscore": 3.0,
        "comments": 3,
        "historyCouponCount": 10,
        "backCateName": "家常菜",
        "areaname": "府前大街",
        "tag": null,
        "cate": [
          1,
          20632,
          20426,
          20557
        ],
        "recentScreen": null,
        "abstracts": null,
        "dangleAbstracts": null,
        "titleTags": [],
        "iUrl": null,
        "deals": null,
        "posdescr": null,
        "ct_poi": null,
        "trace": null,
        "landmarkDistance": null,
        "hasAds": false,
        "adsClickUrl": "",
        "adsShowUrl": "",
        "distance": "",
        "cityId": 127,
        "city": "沧州",
        "full": false
      },
      {
        "id": 97689561,
        "template": "pcfood",
        "imageUrl": "http://p1.meituan.net/w.h/deal/6a306852ef07bbfaeb9101fcdabdcc6a23473.jpg",
        "title": "杨国福麻辣烫（建新路店）",
        "address": "建新路东光镇建新路171号",
        "lowestprice": 0.0,
        "avgprice": 15.0,
        "latitude": 37.885091,
        "longitude": 116.540563,
        "showType": "food",
        "avgscore": 4.1,
        "comments": 114,
        "historyCouponCount": 2005,
        "backCateName": "麻辣烫",
        "areaname": "建新路",
        "tag": null,
        "cate": [
          1,
          20426,
          20557
        ],
        "recentScreen": null,
        "abstracts": null,
        "dangleAbstracts": null,
        "titleTags": [],
        "iUrl": null,
        "deals": null,
        "posdescr": null,
        "ct_poi": null,
        "trace": null,
        "landmarkDistance": null,
        "hasAds": false,
        "adsClickUrl": "",
        "adsShowUrl": "",
        "distance": "",
        "cityId": 127,
        "city": "沧州",
        "full": false
      },
      {
        "id": 190601919,
        "template": "pcfood",
        "imageUrl": "http://p0.meituan.net/feop/d91337976e8f9540e31caaff3eeffd3c57619.png",
        "title": "华莱士炸鸡汉堡（东光店）",
        "address": "东光东祥商场往东100米",
        "lowestprice": 0.0,
        "avgprice": 0.0,
        "latitude": 37.88277,
        "longitude": 116.553169,
        "showType": "food",
        "avgscore": 0.0,
        "comments": 0,
        "historyCouponCount": 0,
        "backCateName": "西餐",
        "areaname": "东光",
        "tag": null,
        "cate": [
          1,
          20632,
          20426,
          20557
        ],
        "recentScreen": null,
        "abstracts": null,
        "dangleAbstracts": null,
        "titleTags": [],
        "iUrl": null,
        "deals": null,
        "posdescr": null,
        "ct_poi": null,
        "trace": null,
        "landmarkDistance": null,
        "hasAds": false,
        "adsClickUrl": "",
        "adsShowUrl": "",
        "distance": "",
        "cityId": 0,
        "city": "",
        "full": false
      },
      {
        "id": 103555523,
        "template": "pcfood",
        "imageUrl": "http://p0.meituan.net/w.h/waimaipoi/8403f580a2d15bf59e3591cf34901e3d44639.jpg",
        "title": "谷连天八宝粥",
        "address": "茧城大街茧城大街279号",
        "lowestprice": 0.0,
        "avgprice": 0.0,
        "latitude": 37.884302,
        "longitude": 116.548382,
        "showType": "food",
        "avgscore": 3.5,
        "comments": 0,
        "historyCouponCount": 0,
        "backCateName": "粥类",
        "areaname": "茧城大街",
        "tag": null,
        "cate": [
          1,
          20426,
          20557
        ],
        "recentScreen": null,
        "abstracts": null,
        "dangleAbstracts": null,
        "titleTags": [],
        "iUrl": null,
        "deals": null,
        "posdescr": null,
        "ct_poi": null,
        "trace": null,
        "landmarkDistance": null,
        "hasAds": false,
        "adsClickUrl": "",
        "adsShowUrl": "",
        "distance": "",
        "cityId": 127,
        "city": "沧州",
        "full": false
      },
      {
        "id": 74471311,
        "template": "pcfood",
        "imageUrl": "http://p0.meituan.net/feop/d91337976e8f9540e31caaff3eeffd3c57619.png",
        "title": "波波烧烤",
        "address": "育才大街育才大街195号",
        "lowestprice": 0.0,
        "avgprice": 0.0,
        "latitude": 37.880835,
        "longitude": 116.544831,
        "showType": "food",
        "avgscore": 3.0,
        "comments": 0,
        "historyCouponCount": 0,
        "backCateName": "烧烤",
        "areaname": "育才大街",
        "tag": null,
        "cate": [
          1,
          20632,
          20426,
          20557
        ],
        "recentScreen": null,
        "abstracts": null,
        "dangleAbstracts": null,
        "titleTags": [],
        "iUrl": null,
        "deals": null,
        "posdescr": null,
        "ct_poi": null,
        "trace": null,
        "landmarkDistance": null,
        "hasAds": false,
        "adsClickUrl": "",
        "adsShowUrl": "",
        "distance": "",
        "cityId": 127,
        "city": "沧州",
        "full": false
      },
      {
        "id": 171856255,
        "template": "pcfood",
        "imageUrl": "http://p1.meituan.net/w.h/waimaipoi/0bc11036c6328ed4cf6a26558c516aaa30813.jpg",
        "title": "凯玲超市",
        "address": "东光东升路东恒基花园三期30幢04号商铺",
        "lowestprice": 0.0,
        "avgprice": 0.0,
        "latitude": 37.890753,
        "longitude": 116.558589,
        "showType": "shopping",
        "avgscore": 0.0,
        "comments": 0,
        "historyCouponCount": 0,
        "backCateName": "超市/便利店",
        "areaname": "东光",
        "tag": null,
        "cate": [
          1,
          387,
          20599
        ],
        "recentScreen": null,
        "abstracts": null,
        "dangleAbstracts": null,
        "titleTags": [],
        "iUrl": null,
        "deals": null,
        "posdescr": null,
        "ct_poi": null,
        "trace": null,
        "landmarkDistance": null,
        "hasAds": false,
        "adsClickUrl": "",
        "adsShowUrl": "",
        "distance": "",
        "cityId": 0,
        "city": "",
        "full": false
      },
      {
        "id": 5872605,
        "template": "pcfood",
        "imageUrl": "https://img.meituan.net/w.h/msmerchant/d19a185b7bd83f53094d2ffe66430d5420972.jpg",
        "title": "德克士（东光店）",
        "address": "东光茧城大街东祥商厦1楼",
        "lowestprice": 0.0,
        "avgprice": 24.0,
        "latitude": 37.883109,
        "longitude": 116.552095,
        "showType": "food",
        "avgscore": 3.9,
        "comments": 111,
        "historyCouponCount": 356,
        "backCateName": "快餐",
        "areaname": "东光",
        "tag": null,
        "cate": [
          1,
          20426,
          20557
        ],
        "recentScreen": null,
        "abstracts": null,
        "dangleAbstracts": null,
        "titleTags": [],
        "iUrl": null,
        "deals": null,
        "posdescr": null,
        "ct_poi": null,
        "trace": null,
        "landmarkDistance": null,
        "hasAds": false,
        "adsClickUrl": "",
        "adsShowUrl": "",
        "distance": "",
        "cityId": 127,
        "city": "沧州",
        "full": false
      },
      {
        "id": 96497832,
        "template": "pcfood",
        "imageUrl": "http://p0.meituan.net/w.h/mogu/7078d0bdd623cc99da79df7d2ebb52cb274109.jpg",
        "title": "沙县小吃",
        "address": "东光府前大街与建新路交叉口旁",
        "lowestprice": 0.0,
        "avgprice": 0.0,
        "latitude": 37.887434,
        "longitude": 116.540777,
        "showType": "food",
        "avgscore": 3.5,
        "comments": 0,
        "historyCouponCount": 0,
        "backCateName": "沙县小吃",
        "areaname": "东光",
        "tag": null,
        "cate": [
          1,
          20426,
          20557
        ],
        "recentScreen": null,
        "abstracts": null,
        "dangleAbstracts": null,
        "titleTags": [],
        "iUrl": null,
        "deals": null,
        "posdescr": null,
        "ct_poi": null,
        "trace": null,
        "landmarkDistance": null,
        "hasAds": false,
        "adsClickUrl": "",
        "adsShowUrl": "",
        "distance": "",
        "cityId": 127,
        "city": "沧州",
        "full": false
      },
      {
        "id": 164947656,
        "template": "pcfood",
        "imageUrl": "http://p0.meituan.net/w.h/xianfu/ab7f2d0d5e33209a87e29e39f976bde836246.jpg",
        "title": "正新鸡排蜜雪冰城（东祥店）",
        "address": "东光迎宾大道富祥一号门市",
        "lowestprice": 0.0,
        "avgprice": 0.0,
        "latitude": 37.88292,
        "longitude": 116.553135,
        "showType": "food",
        "avgscore": 3.5,
        "comments": 0,
        "historyCouponCount": 0,
        "backCateName": "小吃快餐",
        "areaname": "东光",
        "tag": null,
        "cate": [
          1,
          20426,
          20557
        ],
        "recentScreen": null,
        "abstracts": null,
        "dangleAbstracts": null,
        "titleTags": [],
        "iUrl": null,
        "deals": null,
        "posdescr": null,
        "ct_poi": null,
        "trace": null,
        "landmarkDistance": null,
        "hasAds": false,
        "adsClickUrl": "",
        "adsShowUrl": "",
        "distance": "",
        "cityId": 0,
        "city": "",
        "full": false
      },
      {
        "id": 99562962,
        "template": "pcfood",
        "imageUrl": "http://p1.meituan.net/w.h/waimaipoi/94273255dde808bf9df312aabccbdd9453739.jpg",
        "title": "阿桂嫂麻辣烫过桥米线石锅拌饭",
        "address": "茧城大街茧城大街189号",
        "lowestprice": 0.0,
        "avgprice": 0.0,
        "latitude": 37.885628,
        "longitude": 116.541705,
        "showType": "food",
        "avgscore": 3.0,
        "comments": 0,
        "historyCouponCount": 0,
        "backCateName": "麻辣烫",
        "areaname": "茧城大街",
        "tag": null,
        "cate": [
          1,
          20426,
          20557
        ],
        "recentScreen": null,
        "abstracts": null,
        "dangleAbstracts": null,
        "titleTags": [],
        "iUrl": null,
        "deals": null,
        "posdescr": null,
        "ct_poi": null,
        "trace": null,
        "landmarkDistance": null,
        "hasAds": false,
        "adsClickUrl": "",
        "adsShowUrl": "",
        "distance": "",
        "cityId": 127,
        "city": "沧州",
        "full": false
      }
    ],
    "cardExtension": {
      "redirecturl": "imeituan://www.meituan.com/web?url=https%3A%2F%2Fm.dianping.com%2Fnode%2Fpet%2Fhtml%2Fmtindex.html",
      "imageInfos": [
        {
          "img": "https://p1.meituan.net/dprainbow/e5784858815ae8ba0f73e74fb02991a6214835.png",
          "iurl": "imeituan://www.meituan.com/web?url=https%3A%2F%2Fm.dianping.com%2Fnode%2Fpet%2Fhtml%2Fmtindex.html"
        }
      ],
      "trace": {
        "type": "CARD",
        "cateid": "13",
        "id": "417",
        "offset": "0",
        "requestid": "7d9e74e0-f604-459f-9aa8-da93214b022c",
        "globalid": "6761887537133714695",
        "queryid": "237745756308628679"
      },
      "ct_poi": "155582247386038502626604612758156875353_dcard_e6761887537133714695",
      "cateid": "13",
      "cardInfos": [],
      "catetag": "进入频道",
      "id": 417,
      "iconUrl": "https://p0.meituan.net/dprainbow/5365ff41f6fcc0f98b79cb5a8a8c03a23181.png",
      "templateid": "6",
      "title": "美团宠物"
    },
    "extraInfoCinema": null,
    "serverInfo": {
      "traceId": "7d9e74e0-f604-459f-9aa8-da93214b022c",
      "searchId": "8812500863143378550",
      "globalId": "6761887537133714695",
      "queryId": "237745756308628679"
    },
    "stid": null
  }
}